ldlite-3.2.1.dist-info/METADATA
ldlite-3.2.1.dist-info/WHEEL
ldlite-3.2.1.dist-info/entry_points.txt
ldlite-3.2.1.dist-info/licenses/LICENSE
ldlite/__init__.py
ldlite/_camelcase.py
ldlite/_csv.py
ldlite/_database.py
ldlite/_folio.py
ldlite/_jsonx.py
ldlite/_select.py
ldlite/_sqlx.py
ldlite/_xlsx.py
ldlite/py.typed
ldlite-3.2.1.dist-info/RECORD
