Metadata-Version: 2.1
Name: ldlite
Version: 3.2.1
Summary: Lightweight analytics tool for FOLIO services
Author-Email: Katherine Bargar <kbargar@fivecolleges.edu>, Nassib Nassar <nassib@indexdata.com>
License: Apache-2.0
Classifier: License :: OSI Approved :: Apache Software License
Classifier: Operating System :: OS Independent
Classifier: Programming Language :: Python :: 3
Project-URL: Homepage, https://github.com/library-data-platform/ldlite
Project-URL: Bug Tracker, https://github.com/library-data-platform/ldlite/issues
Requires-Python: >=3.9
Requires-Dist: duckdb<1.4,>=0.6.1
Requires-Dist: psycopg2-binary>=2.9.5
Requires-Dist: tqdm>=4.64.1
Requires-Dist: XlsxWriter>=3.0.6
Requires-Dist: httpx-folio>=0.3.0
Requires-Dist: orjson>=3.9
Requires-Dist: psycopg>=3.2.0
